__init__.py
sqlpage/__init__.py
sqlpage/models.py
sqlpage/sqlpage.py
sqlpage-0.1.0.dist-info/LICENSE
sqlpage-0.1.0.dist-info/METADATA
sqlpage-0.1.0.dist-info/WHEEL
sqlpage-0.1.0.dist-info/top_level.txt
sqlpage-0.1.0.dist-info/RECORD
