Metadata-Version: 2.1
Name: sqlpage
Version: 0.1.0
Summary: Python package to add pagination to a model and return bas64 encoded pagination token
Author: Prabhu Pant
Project-URL: Homepage, https://github.com/prabhupant/sqlpage
Project-URL: Issues, https://github.com/prabhupant/sqlpage/issues
Classifier: Programming Language :: Python :: 3
Classifier: License :: OSI Approved :: MIT License
Classifier: Operating System :: OS Independent
Requires-Python: >=3.8
License-File: LICENSE
Requires-Dist: sqlmodel ==0.0.18
Requires-Dist: SQLAlchemy ==2.0.30
